hxrsnd/__init__.py
hxrsnd/_version.py
hxrsnd/aerotech.py
hxrsnd/attocube.py
hxrsnd/bragg.py
hxrsnd/diode.py
hxrsnd/exceptions.py
hxrsnd/macromotor.py
hxrsnd/pneumatic.py
hxrsnd/rtd.py
hxrsnd/run_snd.py
hxrsnd/sequencer.py
hxrsnd/snddevice.py
hxrsnd/sndmotor.py
hxrsnd/sndsystem.py
hxrsnd/tower.py
hxrsnd/utils.py
hxrsnd/version.py
hxrsnd/plans/__init__.py
hxrsnd/plans/alignment.py
hxrsnd/plans/calibration.py
hxrsnd/plans/plan_stubs.py
hxrsnd/plans/preprocessors.py
hxrsnd/plans/scans.py
hxrsnd/screens/diode.ui
hxrsnd/screens/motor_expert_screens.sh
hxrsnd/screens/snd_main
hxrsnd/tests/__init__.py
hxrsnd/tests/conftest.py
hxrsnd/tests/test_aerotech.py
hxrsnd/tests/test_attocube.py
hxrsnd/tests/test_plans_alignment.py
hxrsnd/tests/test_plans_calibration.py
hxrsnd/tests/test_plans_plan_stubs.py
hxrsnd/tests/test_plans_preprocessors.py
hxrsnd/tests/test_plans_scans.py
hxrsnd/tests/test_pneumatic.py
hxrsnd/tests/test_rtd.py
hxrsnd/tests/test_scripts.py
hxrsnd/tests/test_sequencer.py
hxrsnd/tests/test_snd_devices.py
hxrsnd/tests/test_snddevice.py
hxrsnd/tests/test_sndmotor.py
hxrsnd/tests/test_sndsystem.py
hxrsnd/tests/test_tower.py
hxrsnd/tests/test_utils.py
hxrsnd-0.3.3.dist-info/licenses/AUTHORS.rst
hxrsnd-0.3.3.dist-info/licenses/LICENSE.md
hxrsnd-0.3.3.dist-info/METADATA
hxrsnd-0.3.3.dist-info/WHEEL
hxrsnd-0.3.3.dist-info/entry_points.txt
hxrsnd-0.3.3.dist-info/top_level.txt
hxrsnd-0.3.3.dist-info/RECORD
