Metadata-Version: 2.4
Name: hxrsnd
Version: 0.3.3
Summary: Python controls suite for HXRSnD
Author: SLAC National Accelerator Laboratory
License: Copyright (c) 2023, The Board of Trustees of the Leland Stanford Junior
Classifier: Development Status :: 2 - Pre-Alpha
Classifier: Natural Language :: English
Classifier: Programming Language :: Python :: 3
Requires-Python: >=3.9
License-File: LICENSE.md
License-File: AUTHORS.rst
Requires-Dist: numpy
Requires-Dist: pandas
Requires-Dist: lmfit
Requires-Dist: simplejson
Requires-Dist: pyyaml
Requires-Dist: coloredlogs
Requires-Dist: super_state_machine
Requires-Dist: pswalker
Requires-Dist: pcdsdevices
Requires-Dist: ophyd
Provides-Extra: test
Requires-Dist: pytest; extra == "test"
Requires-Dist: pytest-timeout; extra == "test"
Requires-Dist: pytest-cov; extra == "test"
Provides-Extra: doc
Requires-Dist: numpydoc; extra == "doc"
Requires-Dist: ophyd>=1.6.0; extra == "doc"
Requires-Dist: sphinx; extra == "doc"
Requires-Dist: sphinx_rtd_theme; extra == "doc"
Requires-Dist: sphinxcontrib-jquery; extra == "doc"
Dynamic: license-file
